setup.py
flowee/__init__.py
flowee/main.py
flowee/utils.py
flowee.egg-info/PKG-INFO
flowee.egg-info/SOURCES.txt
flowee.egg-info/dependency_links.txt
flowee.egg-info/entry_points.txt
flowee.egg-info/requires.txt
flowee.egg-info/top_level.txt
flowee/web/__init_.py
flowee/web/index.html
flowee/web/package.json
flowee/web/tsconfig.json
flowee/web/tsconfig.node.json
flowee/web/vite.config.ts
flowee/web/yarn.lock
flowee/web/public/vite.svg
flowee/web/public/assets/Bucket.png
flowee/web/public/assets/BucketPolicy.png
flowee/web/public/assets/CacheCluster.png
flowee/web/public/assets/Certificate.png
flowee/web/public/assets/Cluster.png
flowee/web/public/assets/ConfigurationSet.png
flowee/web/public/assets/DBCluster.png
flowee/web/public/assets/DBClusterNep.png
flowee/web/public/assets/Database.png
flowee/web/public/assets/Datastore.png
flowee/web/public/assets/Detector.png
flowee/web/public/assets/Distribution.png
flowee/web/public/assets/EventBus.png
flowee/web/public/assets/Function.png
flowee/web/public/assets/Group.png
flowee/web/public/assets/HostedZone.png
flowee/web/public/assets/Instance.png
flowee/web/public/assets/InstanceConnect.png
flowee/web/public/assets/Key.png
flowee/web/public/assets/Keyspace.png
flowee/web/public/assets/Method.png
flowee/web/public/assets/Protection.png
flowee/web/public/assets/Queue.png
flowee/web/public/assets/Res_AWS-IoT_Policy_48.png
flowee/web/public/assets/RestApi.png
flowee/web/public/assets/Secret.png
flowee/web/public/assets/StateMachine.png
flowee/web/public/assets/Stream.png
flowee/web/public/assets/Table.png
flowee/web/public/assets/TopicRule.png
flowee/web/public/assets/Trail.png
flowee/web/public/assets/UserPool.png
flowee/web/public/assets/VPC.png
flowee/web/public/assets/WebACL.png
flowee/web/public/assets/preact.svg
flowee/web/src/app.tsx
flowee/web/src/constants.ts
flowee/web/src/index.css
flowee/web/src/main.tsx
flowee/web/src/schema.json
flowee/web/src/vite-env.d.ts
flowee/web/src/@types/edges.ts
flowee/web/src/@types/node.ts
flowee/web/src/assets/App.png
flowee/web/src/assets/Arch_AWS-Backup_64@5x.png
flowee/web/src/assets/Arch_AWS-Billing-Conductor_64@5x.png
