Metadata-Version: 2.1
Name: flowee
Version: 1.7
Summary: A CLI tool to create AWS diagrams from Cloudformation templates.
Home-page: UNKNOWN
Author: Westpoint Software Solutions
License: UNKNOWN
Platform: UNKNOWN
